<?xml version="1.0" encoding="utf-8"?>
<databaseChangeLog
    xmlns="http://www.liquibase.org/xml/ns/dbchangelog"
    xmlns:ext="http://www.liquibase.org/xml/ns/dbchangelog-ext"
    xmlns:xsi="http://www.w3.org/2001/XMLSchema-instance"
    xsi:schemaLocation="http://www.liquibase.org/xml/ns/dbchangelog ../xml-schema/dbchangelog-3.6.xsd
                        http://www.liquibase.org/xml/ns/dbchangelog-ext ../xml-schema/dbchangelog-ext.xsd">

    <property name="uuidType" value="uuid" dbms="postgresql, h2"/>
    <property name="uuidFunction" value="uuid_generate_v4()" dbms="postgresql"/>
    <property name="uuidFunction" value="random_uuid()" dbms="h2"/>

    <!--
        Added the entity FieldsDisplaySettings.
    -->
    <changeSet id="20200127211929-1" author="awalkowiak">
        <createTable tableName="fields_display_settings">
            <column name="id" type="${uuidType}" defaultValueComputed="${uuidFunction}">
                <constraints primaryKey="true" nullable="false"/>
            </column>
            <column name="name" type="varchar(255)">
                <constraints nullable="false" />
            </column>

            <column name="user_id" type="UUID">
                <constraints nullable="true" />
            </column>

            <!-- jhipster-needle-liquibase-add-column - JHipster will add columns here, do not remove-->
        </createTable>
    </changeSet>

    <changeSet author="awalkowiak" id="20200127211929-2">
        <createTable tableName="location_fields">
            <column name="fields_display_settings_id" type="UUID">
                <constraints nullable="false"/>
            </column>
            <column name="field_name" type="VARCHAR(255)"/>
        </createTable>
    </changeSet>

    <changeSet author="awalkowiak" id="20200127211929-3">
        <createTable tableName="organization_fields">
            <column name="fields_display_settings_id" type="UUID">
                <constraints nullable="false"/>
            </column>
            <column name="field_name" type="VARCHAR(255)"/>
        </createTable>
    </changeSet>

    <changeSet author="awalkowiak" id="20200127211929-4">
        <createTable tableName="physical_address_fields">
            <column name="fields_display_settings_id" type="UUID">
                <constraints nullable="false"/>
            </column>
            <column name="field_name" type="VARCHAR(255)"/>
        </createTable>
    </changeSet>

    <changeSet author="awalkowiak" id="20200127211929-5">
        <createTable tableName="postal_address_fields">
            <column name="fields_display_settings_id" type="UUID">
                <constraints nullable="false"/>
            </column>
            <column name="field_name" type="VARCHAR(255)"/>
        </createTable>
    </changeSet>

    <changeSet author="awalkowiak" id="20200127211929-6">
        <createTable tableName="service_fields">
            <column name="fields_display_settings_id" type="UUID">
                <constraints nullable="false"/>
            </column>
            <column name="field_name" type="VARCHAR(255)"/>
        </createTable>
    </changeSet>

    <changeSet author="awalkowiak" id="20200127211929-7">
        <createTable tableName="service_taxonomies_details_fields">
            <column name="fields_display_settings_id" type="UUID">
                <constraints nullable="false"/>
            </column>
            <column name="field_name" type="VARCHAR(255)"/>
        </createTable>
    </changeSet>

    <changeSet author="awalkowiak" id="20200127211929-8">
        <createTable tableName="contact_details_fields">
            <column name="fields_display_settings_id" type="UUID">
                <constraints nullable="false"/>
            </column>
            <column name="field_name" type="VARCHAR(255)"/>
        </createTable>
    </changeSet>

    <!-- jhipster-needle-liquibase-add-changeset - JHipster will add changesets here, do not remove-->
</databaseChangeLog>
